README.md
setup.py
instagram_python_scraper.egg-info/PKG-INFO
instagram_python_scraper.egg-info/SOURCES.txt
instagram_python_scraper.egg-info/dependency_links.txt
instagram_python_scraper.egg-info/requires.txt
instagram_python_scraper.egg-info/top_level.txt
instagram_scraper/__init__.py
instagram_scraper/endpoints.py
instagram_scraper/helper.py
instagram_scraper/instagram.py
instagram_scraper/cache/__init__.py
instagram_scraper/cache/cache.py
instagram_scraper/cache/disk_cache.py
instagram_scraper/exception/__init__.py
instagram_scraper/exception/instagram_auth_exception.py
instagram_scraper/exception/instagram_exception.py
instagram_scraper/exception/instagram_not_found_exception.py
instagram_scraper/model/__init__.py
instagram_scraper/model/account.py
instagram_scraper/model/base_model.py
instagram_scraper/model/carousel_media.py
instagram_scraper/model/comment.py
instagram_scraper/model/initializer_model.py
instagram_scraper/model/like.py
instagram_scraper/model/location.py
instagram_scraper/model/media.py
instagram_scraper/model/story.py
instagram_scraper/model/tag.py
instagram_scraper/model/user_stories.py
instagram_scraper/two_step_verification/__init__.py
instagram_scraper/two_step_verification/console_verification.py
instagram_scraper/two_step_verification/two_step_verification.py