Metadata-Version: 1.2
Name: instagram-python-scraper
Version: 1.0.2
Summary: A instagram scraper wrote in python. Various actions supported.Enjoy it!
Home-page: https://github.com/luengwaiban/instagram-python-scraper
Author: leungwaiban
Author-email: 407261380@qq.com
Maintainer: leungwaiban
Maintainer-email: 407261380@qq.com
License: MIT
Platform: all
Classifier: Development Status :: 4 - Beta
Classifier: Operating System :: OS Independent
Classifier: Intended Audience :: Developers
Classifier: License :: OSI Approved :: BSD License
Classifier: Programming Language :: Python
Classifier: Programming Language :: Python :: Implementation
Classifier: Programming Language :: Python :: 3
Classifier: Programming Language :: Python :: 3.4
Classifier: Programming Language :: Python :: 3.5
Classifier: Programming Language :: Python :: 3.6
Classifier: Topic :: Software Development :: Libraries
